pec_dss/__init__.py
pec_dss/__main__.py
pec_dss/cli.py
pec_dss-0.1.1.dist-info/licenses/LICENSE
pec_dss-0.1.1.dist-info/METADATA
pec_dss-0.1.1.dist-info/WHEEL
pec_dss-0.1.1.dist-info/entry_points.txt
pec_dss-0.1.1.dist-info/top_level.txt
pec_dss-0.1.1.dist-info/RECORD
