Metadata-Version: 2.4
Name: pec-dss
Version: 0.1.1
Summary: Paralinguistic Event Classification from Diarized Speaker Segments
Author-email: Hyunwoo Kim <hwk06023@gmail.com>
License: GPL-3.0-only
Project-URL: Homepage, https://github.com/hwk06023/PEC-DSS
Project-URL: Bug Tracker, https://github.com/hwk06023/PEC-DSS/issues
Classifier: Development Status :: 4 - Beta
Classifier: Programming Language :: Python :: 3
Classifier: Programming Language :: Python :: 3.8
Classifier: Programming Language :: Python :: 3.9
Classifier: Programming Language :: Python :: 3.10
Classifier: License :: OSI Approved :: GNU General Public License v3 (GPLv3)
Classifier: Operating System :: OS Independent
Classifier: Topic :: Multimedia :: Sound/Audio :: Analysis
Classifier: Topic :: Multimedia :: Sound/Audio :: Speech
Classifier: Topic :: Scientific/Engineering :: Artificial Intelligence
Requires-Python: >=3.8
License-File: LICENSE
Requires-Dist: torch>=1.10.0
Requires-Dist: torchaudio>=0.10.0
Requires-Dist: librosa>=0.9.1
Requires-Dist: soundfile>=0.10.0
Requires-Dist: numpy>=1.20.0
Requires-Dist: transformers>=4.15.0
Requires-Dist: huggingface_hub>=0.4.0
Requires-Dist: matplotlib>=3.4.0
Provides-Extra: dev
Requires-Dist: pytest>=6.0.0; extra == "dev"
Requires-Dist: pytest-cov>=2.12.0; extra == "dev"
Requires-Dist: black>=21.5b2; extra == "dev"
Requires-Dist: isort>=5.9.1; extra == "dev"
Requires-Dist: flake8>=3.9.2; extra == "dev"
Provides-Extra: docs
Requires-Dist: sphinx>=4.0.2; extra == "docs"
Requires-Dist: sphinx-rtd-theme>=0.5.2; extra == "docs"
Requires-Dist: myst-parser>=0.15.1; extra == "docs"
Dynamic: license-file
